pretix_cas/__init__.py
pretix_cas/auth_backend.py
pretix_cas/forms.py
pretix_cas/models.py
pretix_cas/signals.py
pretix_cas/urls.py
pretix_cas/views.py
pretix_cas/locale/de/LC_MESSAGES/django.mo
pretix_cas/locale/de/LC_MESSAGES/django.po
pretix_cas/locale/de_Informal/LC_MESSAGES/django.mo
pretix_cas/locale/de_Informal/LC_MESSAGES/django.po
pretix_cas/migrations/0001_initial.py
pretix_cas/migrations/__init__.py
pretix_cas/static/pretix_cas/.gitkeep
pretix_cas/templates/pretix_cas/cas_assignment_rule_delete.html
pretix_cas/templates/pretix_cas/cas_assignment_rule_edit.html
pretix_cas/templates/pretix_cas/cas_assignment_rules.html
pretix_cas-1.2.0.dist-info/LICENSE
pretix_cas-1.2.0.dist-info/METADATA
pretix_cas-1.2.0.dist-info/WHEEL
pretix_cas-1.2.0.dist-info/entry_points.txt
pretix_cas-1.2.0.dist-info/top_level.txt
pretix_cas-1.2.0.dist-info/RECORD
