Metadata-Version: 2.1
Name: pretix-cas
Version: 1.2.0
Summary: Apereo CAS authentication backend for pretix
Home-page: https://github.com/DataManagementLab/pretix-cas
Author: Benjamin Haettasch & TU Darmstadt BP Informatik 2019/20 Group 45
Author-email: benjamin.haettasch@cs.tu-darmstadt.de
License: Apache Software License
Platform: UNKNOWN
Classifier: Programming Language :: Python :: 3
Classifier: License :: OSI Approved :: Apache Software License
Classifier: Operating System :: OS Independent
Classifier: Environment :: Web Environment
Classifier: Development Status :: 5 - Production/Stable
Requires-Dist: python-cas (>=1.5.0)
